reportportal_client/__init__.py
reportportal_client/client.py
reportportal_client/errors.py
reportportal_client/_internal/__init__.py
reportportal_client/_internal/http.py
reportportal_client/_internal/aio/__init__.py
reportportal_client/_internal/aio/http.py
reportportal_client/_internal/aio/tasks.py
reportportal_client/_internal/local/__init__.py
reportportal_client/_internal/local/__init__.pyi
reportportal_client/_internal/logs/__init__.py
reportportal_client/_internal/logs/batcher.py
reportportal_client/_internal/services/__init__.py
reportportal_client/_internal/services/auth.py
reportportal_client/_internal/services/client_id.py
reportportal_client/_internal/services/client_id.pyi
reportportal_client/_internal/services/constants.py
reportportal_client/_internal/services/constants.pyi
reportportal_client/_internal/services/statistics.py
reportportal_client/_internal/static/__init__.py
reportportal_client/_internal/static/abstract.py
reportportal_client/_internal/static/defines.py
reportportal_client/aio/__init__.py
reportportal_client/aio/client.py
reportportal_client/aio/tasks.py
reportportal_client/core/__init__.py
reportportal_client/core/rp_file.py
reportportal_client/core/rp_file.pyi
reportportal_client/core/rp_issues.py
reportportal_client/core/rp_issues.pyi
reportportal_client/core/rp_requests.py
reportportal_client/core/rp_responses.py
reportportal_client/core/worker.py
reportportal_client/core/worker.pyi
reportportal_client/helpers/__init__.py
reportportal_client/helpers/common_helpers.py
reportportal_client/helpers/markdown_helpers.py
reportportal_client/logs/__init__.py
reportportal_client/logs/log_manager.py
reportportal_client/logs/log_manager.pyi
reportportal_client/steps/__init__.py
reportportal_client-5.6.6.dist-info/licenses/LICENSE.md
reportportal_client-5.6.6.dist-info/METADATA
reportportal_client-5.6.6.dist-info/WHEEL
reportportal_client-5.6.6.dist-info/top_level.txt
reportportal_client-5.6.6.dist-info/RECORD
