Metadata-Version: 2.4
Name: reportportal-client
Version: 5.6.6
Summary: Python client for ReportPortal v5.
Home-page: https://github.com/reportportal/client-Python
Download-URL: https://github.com/reportportal/client-Python/tarball/5.6.6
Author: ReportPortal Team
Author-email: support@reportportal.io
License: Apache-2.0
Keywords: testing,reporting,reportportal,client
Classifier: Programming Language :: Python :: 3.8
Classifier: Programming Language :: Python :: 3.9
Classifier: Programming Language :: Python :: 3.10
Classifier: Programming Language :: Python :: 3.11
Classifier: Programming Language :: Python :: 3.12
Classifier: Programming Language :: Python :: 3.13
License-File: LICENSE.md
Requires-Dist: aenum
Requires-Dist: typing-extensions>=4.13.2
Requires-Dist: requests>=2.32.3
Requires-Dist: aiohttp>=3.10.11
Requires-Dist: certifi>=2024.8.30
Dynamic: author
Dynamic: author-email
Dynamic: classifier
Dynamic: description
Dynamic: description-content-type
Dynamic: download-url
Dynamic: home-page
Dynamic: keywords
Dynamic: license
Dynamic: license-file
Dynamic: requires-dist
Dynamic: summary
